shaarli_client/__init__.py
shaarli_client/config.py
shaarli_client/main.py
shaarli_client/utils.py
shaarli_client/client/__init__.py
shaarli_client/client/v1.py
shaarli_client-0.5.0.dist-info/LICENSE
shaarli_client-0.5.0.dist-info/METADATA
shaarli_client-0.5.0.dist-info/WHEEL
shaarli_client-0.5.0.dist-info/entry_points.txt
shaarli_client-0.5.0.dist-info/top_level.txt
shaarli_client-0.5.0.dist-info/RECORD
