Metadata-Version: 2.1
Name: shaarli-client
Version: 0.5.0
Summary: CLI to interact with a Shaarli instance
Home-page: https://github.com/shaarli/python-shaarli-client
Author: The Shaarli Community
Maintainer: VirtualTam
Maintainer-email: virtualtam@flibidi.net
License: MIT
Keywords: bookmark bookmarking shaarli social
Platform: UNKNOWN
Classifier: Development Status :: 3 - Alpha
Classifier: Environment :: Console
Classifier: Intended Audience :: Developers
Classifier: Intended Audience :: End Users/Desktop
Classifier: License :: OSI Approved :: MIT License
Classifier: Natural Language :: English
Classifier: Operating System :: OS Independent
Classifier: Programming Language :: Python
Classifier: Programming Language :: Python :: 3
Classifier: Programming Language :: Python :: 3.6
Classifier: Programming Language :: Python :: 3.7
Classifier: Programming Language :: Python :: 3.8
Classifier: Programming Language :: Python :: 3.9
Classifier: Topic :: Utilities
Requires-Dist: pyjwt (==2.4.0)
Requires-Dist: requests (>=2.25)
